[
  {
    "id": 2,
    "name": "Fibre",
    "slug": "fibre-broadband",
    "sort_order": 2,
    "notices": {
      "open": [
        {
          "id": 16948,
          "title": "Metrofibre Outage | Kempton Park",
          "description": "Metrofibre has informed us of a network outage affecting Kempton Park, affected clients will experience limited to no connectivity. Metrofibre engineers are working on resolving this issue as soon as possible. We sincerely apologize for any inconvenience caused.",
          "resolution": null,
          "product_id": 2,
          "impact_id": 3,
          "expires_at": null,
          "resolved_at": null,
          "should_notify": 0,
          "created_at": "2026-02-21 10:45:24",
          "product": {
            "id": 2,
            "name": "Fibre",
            "slug": "fibre-broadband",
            "sort_order": 2,
            "description": null,
            "has_location": 1
          },
          "impact": {
            "id": 3,
            "name": "Medium Impact",
            "slug": "medium-impact",
            "description": "A few problems",
            "order": 2
          },
          "categories": [
            {
              "id": 9,
              "name": "MetroFibre",
              "slug": "metrofibre",
              "product_id": 2,
              "deleted_at": null,
              "pivot": {
                "notice_id": 16948,
                "category_id": 9
              }
            }
          ],
          "updates": [],
          "provinces": [
            {
              "id": 1,
              "name": "Gauteng",
              "slug": "gauteng"
            }
          ],
          "cities": [
            {
              "id": 48,
              "name": "Kempton Park",
              "slug": "kempton-park",
              "province_id": 1
            }
          ],
          "suburbs": []
        },
        {
          "id": 16947,
          "title": "Metrofibre Outage |  Alberton Retirement Village",
          "description": "Metrofibre has informed us of a network outage affecting  Alberton Retirement Village, affected clients will experience limited to no connectivity. Metrofibre engineers are working on resolving this issue as soon as possible. We sincerely apologize for any inconvenience caused.",
          "resolution": null,
          "product_id": 2,
          "impact_id": 3,
          "expires_at": null,
          "resolved_at": null,
          "should_notify": 0,
          "created_at": "2026-02-21 08:08:33",
          "product": {
            "id": 2,
            "name": "Fibre",
            "slug": "fibre-broadband",
            "sort_order": 2,
            "description": null,
            "has_location": 1
          },
          "impact": {
            "id": 3,
            "name": "Medium Impact",
            "slug": "medium-impact",
            "description": "A few problems",
            "order": 2
          },
          "categories": [
            {
              "id": 9,
              "name": "MetroFibre",
              "slug": "metrofibre",
              "product_id": 2,
              "deleted_at": null,
              "pivot": {
                "notice_id": 16947,
                "category_id": 9
              }
            }
          ],
          "updates": [],
          "provinces": [
            {
              "id": 1,
              "name": "Gauteng",
              "slug": "gauteng"
            }
          ],
          "cities": [
            {
              "id": 21,
              "name": "Alberton",
              "slug": "alberton",
              "province_id": 1
            }
          ],
          "suburbs": []
        },
        {
          "id": 16946,
          "title": "Vumatel Reach Outage | Eldorado Park & Devland",
          "description": "Vumatel Reach has informed us of a network outage affecting Eldorado Park & Devland, affected clients will experience limited to no connectivity. Vumatel Reach engineers are working on resolving this issue as soon as possible. We sincerely apologize for any inconvenience caused.",
          "resolution": null,
          "product_id": 2,
          "impact_id": 3,
          "expires_at": null,
          "resolved_at": null,
          "should_notify": 0,
          "created_at": "2026-02-21 07:28:48",
          "product": {
            "id": 2,
            "name": "Fibre",
            "slug": "fibre-broadband",
            "sort_order": 2,
            "description": null,
            "has_location": 1
          },
          "impact": {
            "id": 3,
            "name": "Medium Impact",
            "slug": "medium-impact",
            "description": "A few problems",
            "order": 2
          },
          "categories": [
            {
              "id": 27,
              "name": "Vuma Reach",
              "slug": "vuma-reach",
              "product_id": 2,
              "deleted_at": null,
              "pivot": {
                "notice_id": 16946,
                "category_id": 27
              }
            }
          ],
          "updates": [],
          "provinces": [
            {
              "id": 1,
              "name": "Gauteng",
              "slug": "gauteng"
            }
          ],
          "cities": [
            {
              "id": 17,
              "name": "Soweto",
              "slug": "soweto",
              "province_id": 1
            },
            {
              "id": 8,
              "name": "Johannesburg",
              "slug": "johannesburg",
              "province_id": 1
            }
          ],
          "suburbs": [
            {
              "id": 2155,
              "name": "Devland",
              "slug": "devland",
              "city_id": 8
            },
            {
              "id": 1307,
              "name": "Eldorado Park",
              "slug": "eldorado-park",
              "city_id": 17
            }
          ]
        },
        {
          "id": 16938,
          "title": "Openserve outage | Richmond",
          "description": "Openserve has informed us of a network outage affecting Richmond, affected clients will experience limited to no connectivity. Openserve engineers are working on resolving this issue as soon as possible. We sincerely apologize for any inconvenience caused.",
          "resolution": null,
          "product_id": 2,
          "impact_id": 3,
          "expires_at": null,
          "resolved_at": null,
          "should_notify": 0,
          "created_at": "2026-02-19 09:33:47",
          "product": {
            "id": 2,
            "name": "Fibre",
            "slug": "fibre-broadband",
            "sort_order": 2,
            "description": null,
            "has_location": 1
          },
          "impact": {
            "id": 3,
            "name": "Medium Impact",
            "slug": "medium-impact",
            "description": "A few problems",
            "order": 2
          },
          "categories": [
            {
              "id": 14,
              "name": "Openserve",
              "slug": "openserve",
              "product_id": 2,
              "deleted_at": null,
              "pivot": {
                "notice_id": 16938,
                "category_id": 14
              }
            }
          ],
          "updates": [],
          "provinces": [
            {
              "id": 3,
              "name": "Western Cape",
              "slug": "western-cape"
            }
          ],
          "cities": [
            {
              "id": 240,
              "name": "Cape Town",
              "slug": "cape-town",
              "province_id": 3
            }
          ],
          "suburbs": [
            {
              "id": 4075,
              "name": "Richmond Park",
              "slug": "richmond-park",
              "city_id": 240
            }
          ]
        },
        {
          "id": 16937,
          "title": "Openserve outage | Margate",
          "description": "Openserve has informed us of a network outage affecting Margate, affected clients will experience limited to no connectivity. Openserve engineers are working on resolving this issue as soon as possible. We sincerely apologize for any inconvenience caused.",
          "resolution": null,
          "product_id": 2,
          "impact_id": 3,
          "expires_at": null,
          "resolved_at": null,
          "should_notify": 0,
          "created_at": "2026-02-19 07:45:01",
          "product": {
            "id": 2,
            "name": "Fibre",
            "slug": "fibre-broadband",
            "sort_order": 2,
            "description": null,
            "has_location": 1
          },
          "impact": {
            "id": 3,
            "name": "Medium Impact",
            "slug": "medium-impact",
            "description": "A few problems",
            "order": 2
          },
          "categories": [
            {
              "id": 14,
              "name": "Openserve",
              "slug": "openserve",
              "product_id": 2,
              "deleted_at": null,
              "pivot": {
                "notice_id": 16937,
                "category_id": 14
              }
            }
          ],
          "updates": [],
          "provinces": [
            {
              "id": 2,
              "name": "KwaZulu-Natal",
              "slug": "kwazulu-natal"
            }
          ],
          "cities": [
            {
              "id": 81,
              "name": "Margate",
              "slug": "margate",
              "province_id": 2
            }
          ],
          "suburbs": []
        },
        {
          "id": 16934,
          "title": "Vumatel Outage | Witpoortjie",
          "description": "Vumatel has informed us of a network outage affecting Witpoortjie, affected clients will experience limited to no connectivity. Vumatel engineers are working on resolving this issue as soon as possible. We sincerely apologize for any inconvenience caused.",
          "resolution": null,
          "product_id": 2,
          "impact_id": 3,
          "expires_at": null,
          "resolved_at": null,
          "should_notify": 0,
          "created_at": "2026-02-18 06:10:12",
          "product": {
            "id": 2,
            "name": "Fibre",
            "slug": "fibre-broadband",
            "sort_order": 2,
            "description": null,
            "has_location": 1
          },
          "impact": {
            "id": 3,
            "name": "Medium Impact",
            "slug": "medium-impact",
            "description": "A few problems",
            "order": 2
          },
          "categories": [
            {
              "id": 18,
              "name": "Vumatel",
              "slug": "vumatel",
              "product_id": 2,
              "deleted_at": null,
              "pivot": {
                "notice_id": 16934,
                "category_id": 18
              }
            }
          ],
          "updates": [],
          "provinces": [
            {
              "id": 1,
              "name": "Gauteng",
              "slug": "gauteng"
            }
          ],
          "cities": [
            {
              "id": 35,
              "name": "Roodepoort",
              "slug": "roodepoort",
              "province_id": 1
            }
          ],
          "suburbs": [
            {
              "id": 413,
              "name": "Witpoortjie",
              "slug": "witpoortjie",
              "city_id": 35
            }
          ]
        },
        {
          "id": 13572,
          "title": "Vumatel installation and maintenance problems | Khayelitsha & Delft",
          "description": "We would like to inform you about the challenges that we are currently experiencing with installation & maintenance activities in the Khayelitsha and Delft areas, Western Cape. Due to increased violence in this area, our contractor partners are not able to freely access the area to work. All maintenance and installation activities in this area will be on hold until further notice. The safety of our contractor partners remains our priority.",
          "resolution": null,
          "product_id": 2,
          "impact_id": 3,
          "expires_at": null,
          "resolved_at": null,
          "should_notify": 0,
          "created_at": "2024-04-08 10:22:57",
          "product": {
            "id": 2,
            "name": "Fibre",
            "slug": "fibre-broadband",
            "sort_order": 2,
            "description": null,
            "has_location": 1
          },
          "impact": {
            "id": 3,
            "name": "Medium Impact",
            "slug": "medium-impact",
            "description": "A few problems",
            "order": 2
          },
          "categories": [
            {
              "id": 24,
              "name": "Vumatel Aerial",
              "slug": "vuma-aerial",
              "product_id": 2,
              "deleted_at": null,
              "pivot": {
                "notice_id": 13572,
                "category_id": 24
              }
            },
            {
              "id": 27,
              "name": "Vuma Reach",
              "slug": "vuma-reach",
              "product_id": 2,
              "deleted_at": null,
              "pivot": {
                "notice_id": 13572,
                "category_id": 27
              }
            }
          ],
          "updates": [
            {
              "id": 989,
              "notice_id": 13572,
              "content": "Delft will be put on hold due to hostility with local gangs. No maintenance and installations will take place. Contractors are not able to enter the area.",
              "created_by_id": 12,
              "created_at": "2025-07-18 21:41:41"
            }
          ],
          "provinces": [
            {
              "id": 3,
              "name": "Western Cape",
              "slug": "western-cape"
            }
          ],
          "cities": [
            {
              "id": 204,
              "name": "Khayelitsha",
              "slug": "khayelitsha",
              "province_id": 3
            },
            {
              "id": 291,
              "name": "Delft",
              "slug": "delft",
              "province_id": 3
            }
          ],
          "suburbs": []
        },
        {
          "id": 16933,
          "title": "Vumatel Maintenance | Lansdowne & Kenwyn",
          "description": "Vumatel is conducting maintenance in Lansdowne & Kenwyn from 2026/02/23, 22:00 to 2026/02/24, 05:00 users affected will experience limited to no connectivity during the maintenance window. We apologize for any inconvenience caused.",
          "resolution": null,
          "product_id": 2,
          "impact_id": 1,
          "expires_at": null,
          "resolved_at": null,
          "should_notify": 0,
          "created_at": "2026-02-18 05:51:09",
          "product": {
            "id": 2,
            "name": "Fibre",
            "slug": "fibre-broadband",
            "sort_order": 2,
            "description": null,
            "has_location": 1
          },
          "impact": {
            "id": 1,
            "name": "Maintenance",
            "slug": "maintenance",
            "description": "Maintenance",
            "order": 0
          },
          "categories": [
            {
              "id": 18,
              "name": "Vumatel",
              "slug": "vumatel",
              "product_id": 2,
              "deleted_at": null,
              "pivot": {
                "notice_id": 16933,
                "category_id": 18
              }
            }
          ],
          "updates": [],
          "provinces": [
            {
              "id": 3,
              "name": "Western Cape",
              "slug": "western-cape"
            }
          ],
          "cities": [
            {
              "id": 240,
              "name": "Cape Town",
              "slug": "cape-town",
              "province_id": 3
            }
          ],
          "suburbs": [
            {
              "id": 3423,
              "name": "Kenwyn",
              "slug": "kenwyn",
              "city_id": 240
            },
            {
              "id": 1199,
              "name": "Lansdowne",
              "slug": "lansdowne",
              "city_id": 240
            }
          ]
        },
        {
          "id": 16915,
          "title": "Vumatel Maintenance | Eden Park",
          "description": "Vumatel is conducting maintenance in Eden Park on the 2026/02/24, 02:00 to 2026/02/24, 06:00, users affected will experience limited to no connectivity during the maintenance window. We apologize for any inconvenience caused.",
          "resolution": null,
          "product_id": 2,
          "impact_id": 1,
          "expires_at": null,
          "resolved_at": null,
          "should_notify": 0,
          "created_at": "2026-02-13 17:30:16",
          "product": {
            "id": 2,
            "name": "Fibre",
            "slug": "fibre-broadband",
            "sort_order": 2,
            "description": null,
            "has_location": 1
          },
          "impact": {
            "id": 1,
            "name": "Maintenance",
            "slug": "maintenance",
            "description": "Maintenance",
            "order": 0
          },
          "categories": [
            {
              "id": 27,
              "name": "Vuma Reach",
              "slug": "vuma-reach",
              "product_id": 2,
              "deleted_at": null,
              "pivot": {
                "notice_id": 16915,
                "category_id": 27
              }
            },
            {
              "id": 18,
              "name": "Vumatel",
              "slug": "vumatel",
              "product_id": 2,
              "deleted_at": null,
              "pivot": {
                "notice_id": 16915,
                "category_id": 18
              }
            },
            {
              "id": 15,
              "name": "Vuma Villages",
              "slug": "vuma-villages",
              "product_id": 2,
              "deleted_at": null,
              "pivot": {
                "notice_id": 16915,
                "category_id": 15
              }
            },
            {
              "id": 24,
              "name": "Vumatel Aerial",
              "slug": "vuma-aerial",
              "product_id": 2,
              "deleted_at": null,
              "pivot": {
                "notice_id": 16915,
                "category_id": 24
              }
            }
          ],
          "updates": [],
          "provinces": [
            {
              "id": 1,
              "name": "Gauteng",
              "slug": "gauteng"
            }
          ],
          "cities": [
            {
              "id": 21,
              "name": "Alberton",
              "slug": "alberton",
              "province_id": 1
            }
          ],
          "suburbs": [
            {
              "id": 3897,
              "name": "Eden Park",
              "slug": "eden-park",
              "city_id": 21
            }
          ]
        }
      ],
      "closed": [
        {
          "id": 16932,
          "title": "Metrofibre outage | Sun Valley, Carlswald",
          "description": "Metrofibre has informed us of a network outage affecting Sun Valley, Carlswald, affected clients will experience limited to no connectivity. Metrofibre engineers are working on resolving this issue as soon as possible. We sincerely apologize for any inconvenience caused.",
          "resolution": null,
          "product_id": 2,
          "impact_id": 3,
          "expires_at": null,
          "resolved_at": "2026-02-21 18:03:52",
          "should_notify": 0,
          "created_at": "2026-02-17 21:03:50",
          "product": {
            "id": 2,
            "name": "Fibre",
            "slug": "fibre-broadband",
            "sort_order": 2,
            "description": null,
            "has_location": 1
          },
          "impact": {
            "id": 3,
            "name": "Medium Impact",
            "slug": "medium-impact",
            "description": "A few problems",
            "order": 2
          },
          "categories": [
            {
              "id": 9,
              "name": "MetroFibre",
              "slug": "metrofibre",
              "product_id": 2,
              "deleted_at": null,
              "pivot": {
                "notice_id": 16932,
                "category_id": 9
              }
            }
          ],
          "updates": [],
          "provinces": [
            {
              "id": 1,
              "name": "Gauteng",
              "slug": "gauteng"
            }
          ],
          "cities": [
            {
              "id": 50,
              "name": "Midrand",
              "slug": "midrand",
              "province_id": 1
            }
          ],
          "suburbs": [
            {
              "id": 708,
              "name": "Carlswald",
              "slug": "carlswald",
              "city_id": 50
            }
          ]
        },
        {
          "id": 16935,
          "title": "Frogfoot Outage | Fishhoek, Sunnydale & Franschhoek",
          "description": "Frogfoot has informed us of a network outage affecting Fishhoek, Sunnydale & Franschhoek, affected clients will experience limited to no connectivity. Frogfoot engineers are working on resolving this issue as soon as possible. We sincerely apologize for any inconvenience caused.",
          "resolution": null,
          "product_id": 2,
          "impact_id": 3,
          "expires_at": null,
          "resolved_at": "2026-02-18 12:30:36",
          "should_notify": 0,
          "created_at": "2026-02-18 11:54:12",
          "product": {
            "id": 2,
            "name": "Fibre",
            "slug": "fibre-broadband",
            "sort_order": 2,
            "description": null,
            "has_location": 1
          },
          "impact": {
            "id": 3,
            "name": "Medium Impact",
            "slug": "medium-impact",
            "description": "A few problems",
            "order": 2
          },
          "categories": [
            {
              "id": 7,
              "name": "Frogfoot",
              "slug": "frogfoot",
              "product_id": 2,
              "deleted_at": null,
              "pivot": {
                "notice_id": 16935,
                "category_id": 7
              }
            }
          ],
          "updates": [],
          "provinces": [
            {
              "id": 3,
              "name": "Western Cape",
              "slug": "western-cape"
            }
          ],
          "cities": [
            {
              "id": 240,
              "name": "Cape Town",
              "slug": "cape-town",
              "province_id": 3
            },
            {
              "id": 246,
              "name": "Franschhoek",
              "slug": "franschhoek",
              "province_id": 3
            }
          ],
          "suburbs": []
        },
        {
          "id": 16936,
          "title": "Frogfoot Outage | Parklands",
          "description": "Frogfoot has informed us of a network outage affecting Parklands, affected clients will experience limited to no connectivity. Frogfoot engineers are working on resolving this issue as soon as possible. We sincerely apologize for any inconvenience caused.",
          "resolution": null,
          "product_id": 2,
          "impact_id": 3,
          "expires_at": null,
          "resolved_at": "2026-02-21 17:58:12",
          "should_notify": 0,
          "created_at": "2026-02-18 12:30:18",
          "product": {
            "id": 2,
            "name": "Fibre",
            "slug": "fibre-broadband",
            "sort_order": 2,
            "description": null,
            "has_location": 1
          },
          "impact": {
            "id": 3,
            "name": "Medium Impact",
            "slug": "medium-impact",
            "description": "A few problems",
            "order": 2
          },
          "categories": [
            {
              "id": 7,
              "name": "Frogfoot",
              "slug": "frogfoot",
              "product_id": 2,
              "deleted_at": null,
              "pivot": {
                "notice_id": 16936,
                "category_id": 7
              }
            }
          ],
          "updates": [],
          "provinces": [
            {
              "id": 3,
              "name": "Western Cape",
              "slug": "western-cape"
            }
          ],
          "cities": [
            {
              "id": 240,
              "name": "Cape Town",
              "slug": "cape-town",
              "province_id": 3
            }
          ],
          "suburbs": []
        },
        {
          "id": 16939,
          "title": "Frogfoot Outage | Port Elizabeth",
          "description": "Frogfoot has informed us of a network outage affecting Port Elizabeth, affected clients will experience limited to no connectivity. Frogfoot engineers are working on resolving this issue as soon as possible. We sincerely apologize for any inconvenience caused.",
          "resolution": null,
          "product_id": 2,
          "impact_id": 3,
          "expires_at": null,
          "resolved_at": "2026-02-19 16:10:50",
          "should_notify": 0,
          "created_at": "2026-02-19 12:46:13",
          "product": {
            "id": 2,
            "name": "Fibre",
            "slug": "fibre-broadband",
            "sort_order": 2,
            "description": null,
            "has_location": 1
          },
          "impact": {
            "id": 3,
            "name": "Medium Impact",
            "slug": "medium-impact",
            "description": "A few problems",
            "order": 2
          },
          "categories": [
            {
              "id": 7,
              "name": "Frogfoot",
              "slug": "frogfoot",
              "product_id": 2,
              "deleted_at": null,
              "pivot": {
                "notice_id": 16939,
                "category_id": 7
              }
            }
          ],
          "updates": [],
          "provinces": [
            {
              "id": 6,
              "name": "Eastern Cape",
              "slug": "eastern-cape"
            }
          ],
          "cities": [
            {
              "id": 458,
              "name": "Port Elizabeth",
              "slug": "port-elizabeth",
              "province_id": 6
            }
          ],
          "suburbs": []
        },
        {
          "id": 16940,
          "title": "Openserve outage | Pinelands",
          "description": "Openserve has informed us of a network outage affecting Pinelands, affected clients will experience limited to no connectivity. Openserve engineers are working on resolving this issue as soon as possible. We sincerely apologize for any inconvenience caused.",
          "resolution": null,
          "product_id": 2,
          "impact_id": 3,
          "expires_at": null,
          "resolved_at": "2026-02-21 17:58:23",
          "should_notify": 0,
          "created_at": "2026-02-19 14:15:15",
          "product": {
            "id": 2,
            "name": "Fibre",
            "slug": "fibre-broadband",
            "sort_order": 2,
            "description": null,
            "has_location": 1
          },
          "impact": {
            "id": 3,
            "name": "Medium Impact",
            "slug": "medium-impact",
            "description": "A few problems",
            "order": 2
          },
          "categories": [
            {
              "id": 14,
              "name": "Openserve",
              "slug": "openserve",
              "product_id": 2,
              "deleted_at": null,
              "pivot": {
                "notice_id": 16940,
                "category_id": 14
              }
            }
          ],
          "updates": [],
          "provinces": [
            {
              "id": 3,
              "name": "Western Cape",
              "slug": "western-cape"
            }
          ],
          "cities": [
            {
              "id": 240,
              "name": "Cape Town",
              "slug": "cape-town",
              "province_id": 3
            }
          ],
          "suburbs": [
            {
              "id": 743,
              "name": "Pinelands",
              "slug": "pinelands",
              "city_id": 240
            }
          ]
        },
        {
          "id": 16941,
          "title": "Openserve Outage | George",
          "description": "Openserve has informed us of a network outage affecting George, affected clients will experience limited to no connectivity. Openserve engineers are working on resolving this issue as soon as possible. We sincerely apologize for any inconvenience caused.",
          "resolution": null,
          "product_id": 2,
          "impact_id": 3,
          "expires_at": null,
          "resolved_at": "2026-02-20 17:18:42",
          "should_notify": 0,
          "created_at": "2026-02-19 15:00:40",
          "product": {
            "id": 2,
            "name": "Fibre",
            "slug": "fibre-broadband",
            "sort_order": 2,
            "description": null,
            "has_location": 1
          },
          "impact": {
            "id": 3,
            "name": "Medium Impact",
            "slug": "medium-impact",
            "description": "A few problems",
            "order": 2
          },
          "categories": [
            {
              "id": 14,
              "name": "Openserve",
              "slug": "openserve",
              "product_id": 2,
              "deleted_at": null,
              "pivot": {
                "notice_id": 16941,
                "category_id": 14
              }
            }
          ],
          "updates": [],
          "provinces": [
            {
              "id": 3,
              "name": "Western Cape",
              "slug": "western-cape"
            }
          ],
          "cities": [
            {
              "id": 247,
              "name": "George",
              "slug": "george",
              "province_id": 3
            }
          ],
          "suburbs": []
        },
        {
          "id": 16942,
          "title": "Vuma Reach outage | Alexandra",
          "description": "Vuma Reach has informed us of a network outage affecting Alexandra, affected clients will experience limited to no connectivity. Vuma Reach engineers are working on resolving this issue as soon as possible. We sincerely apologize for any inconvenience caused.",
          "resolution": null,
          "product_id": 2,
          "impact_id": 3,
          "expires_at": null,
          "resolved_at": "2026-02-19 19:07:50",
          "should_notify": 0,
          "created_at": "2026-02-19 18:00:58",
          "product": {
            "id": 2,
            "name": "Fibre",
            "slug": "fibre-broadband",
            "sort_order": 2,
            "description": null,
            "has_location": 1
          },
          "impact": {
            "id": 3,
            "name": "Medium Impact",
            "slug": "medium-impact",
            "description": "A few problems",
            "order": 2
          },
          "categories": [
            {
              "id": 27,
              "name": "Vuma Reach",
              "slug": "vuma-reach",
              "product_id": 2,
              "deleted_at": null,
              "pivot": {
                "notice_id": 16942,
                "category_id": 27
              }
            }
          ],
          "updates": [],
          "provinces": [
            {
              "id": 1,
              "name": "Gauteng",
              "slug": "gauteng"
            }
          ],
          "cities": [
            {
              "id": 8,
              "name": "Johannesburg",
              "slug": "johannesburg",
              "province_id": 1
            }
          ],
          "suburbs": [
            {
              "id": 3326,
              "name": "Alexandra",
              "slug": "alexandra",
              "city_id": 8
            }
          ]
        },
        {
          "id": 16943,
          "title": "Openserve Outage | Western Cape",
          "description": "Opebserve has informed us of a network outage affecting parts of the Western Cape, affected clients will experience limited to no connectivity.{FNO} engineers are working on resolving this issue as soon as possible. We sincerely apologize for any inconvenience caused.",
          "resolution": null,
          "product_id": 2,
          "impact_id": 3,
          "expires_at": null,
          "resolved_at": "2026-02-20 17:18:01",
          "should_notify": 0,
          "created_at": "2026-02-20 07:47:00",
          "product": {
            "id": 2,
            "name": "Fibre",
            "slug": "fibre-broadband",
            "sort_order": 2,
            "description": null,
            "has_location": 1
          },
          "impact": {
            "id": 3,
            "name": "Medium Impact",
            "slug": "medium-impact",
            "description": "A few problems",
            "order": 2
          },
          "categories": [
            {
              "id": 14,
              "name": "Openserve",
              "slug": "openserve",
              "product_id": 2,
              "deleted_at": null,
              "pivot": {
                "notice_id": 16943,
                "category_id": 14
              }
            }
          ],
          "updates": [],
          "provinces": [
            {
              "id": 3,
              "name": "Western Cape",
              "slug": "western-cape"
            }
          ],
          "cities": [],
          "suburbs": []
        },
        {
          "id": 16944,
          "title": "Evotel outage | Riebeeckstad and Odendaalrus",
          "description": "Evotel has informed us of a network outage affecting Riebeeckstad and Odendaalrus, affected clients will experience limited to no connectivity. Evotel engineers are working on resolving this issue as soon as possible. We sincerely apologize for any inconvenience caused.",
          "resolution": null,
          "product_id": 2,
          "impact_id": 3,
          "expires_at": null,
          "resolved_at": "2026-02-20 19:52:26",
          "should_notify": 0,
          "created_at": "2026-02-20 17:52:06",
          "product": {
            "id": 2,
            "name": "Fibre",
            "slug": "fibre-broadband",
            "sort_order": 2,
            "description": null,
            "has_location": 1
          },
          "impact": {
            "id": 3,
            "name": "Medium Impact",
            "slug": "medium-impact",
            "description": "A few problems",
            "order": 2
          },
          "categories": [
            {
              "id": 6,
              "name": "Evotel",
              "slug": "evotel",
              "product_id": 2,
              "deleted_at": null,
              "pivot": {
                "notice_id": 16944,
                "category_id": 6
              }
            }
          ],
          "updates": [],
          "provinces": [
            {
              "id": 7,
              "name": "Free State",
              "slug": "free-state"
            }
          ],
          "cities": [
            {
              "id": 594,
              "name": "Welkom",
              "slug": "welkom",
              "province_id": 7
            },
            {
              "id": 583,
              "name": "Odendaalsrus",
              "slug": "odendaalsrus",
              "province_id": 7
            }
          ],
          "suburbs": []
        },
        {
          "id": 16945,
          "title": "Vumatel Reach Outage | Eldorado Park",
          "description": "Vumatel Reach has informed us of a network outage affecting Eldorado Park, affected clients will experience limited to no connectivity. Vumatel Reach engineers are working on resolving this issue as soon as possible. We sincerely apologize for any inconvenience caused.",
          "resolution": null,
          "product_id": 2,
          "impact_id": 3,
          "expires_at": null,
          "resolved_at": "2026-02-21 07:27:57",
          "should_notify": 0,
          "created_at": "2026-02-21 07:25:41",
          "product": {
            "id": 2,
            "name": "Fibre",
            "slug": "fibre-broadband",
            "sort_order": 2,
            "description": null,
            "has_location": 1
          },
          "impact": {
            "id": 3,
            "name": "Medium Impact",
            "slug": "medium-impact",
            "description": "A few problems",
            "order": 2
          },
          "categories": [
            {
              "id": 27,
              "name": "Vuma Reach",
              "slug": "vuma-reach",
              "product_id": 2,
              "deleted_at": null,
              "pivot": {
                "notice_id": 16945,
                "category_id": 27
              }
            }
          ],
          "updates": [],
          "provinces": [
            {
              "id": 1,
              "name": "Gauteng",
              "slug": "gauteng"
            }
          ],
          "cities": [
            {
              "id": 17,
              "name": "Soweto",
              "slug": "soweto",
              "province_id": 1
            }
          ],
          "suburbs": [
            {
              "id": 1307,
              "name": "Eldorado Park",
              "slug": "eldorado-park",
              "city_id": 17
            }
          ]
        }
      ]
    },
    "impact": {
      "id": 3,
      "name": "Medium Impact",
      "slug": "medium-impact",
      "description": "A few problems",
      "order": 2
    }
  }
]
